minihex/HexGame.py
minihex/__init__.py
minihex-1.0.1.dist-info/LICENSE
minihex-1.0.1.dist-info/METADATA
minihex-1.0.1.dist-info/WHEEL
minihex-1.0.1.dist-info/top_level.txt
minihex-1.0.1.dist-info/RECORD
