Metadata-Version: 2.1
Name: minihex
Version: 1.0.1
Summary: The game of Hex implemented for reinforcement learning in the OpenAI gym framework. Optimized for rollout speed.
Home-page: https://github.com/FirefoxMetzger/minihex.git
Author: Sebastian Wallkotter
Author-email: sebastian@wallkoetter.net
License: UNKNOWN
Platform: UNKNOWN
Classifier: Programming Language :: Python :: 3
Classifier: License :: OSI Approved :: MIT License
Classifier: Operating System :: OS Independent
Requires-Python: >=3.7
Requires-Dist: numpy (>=1.18.2)
Requires-Dist: gym (>=0.17.1)
